zodchy_identity/__init__.py
zodchy_identity/uuids.py
zodchy_identity-0.1.1.dist-info/METADATA
zodchy_identity-0.1.1.dist-info/WHEEL
zodchy_identity-0.1.1.dist-info/RECORD
